[
    {
        "Tên sản phẩm": "Quần Jeans Slimfit Co Giãn The Original 28 Xanh Đậm 1",
        "Màu sắc": "",
        "Ảnh": [
            "//yame.vn/cdn/shop/files/qu-n-jean-the-original-28-xanh-d-m-1-1174882642.jpg?v=1750786684&width=1946",
            "//yame.vn/cdn/shop/files/qu-n-jean-the-original-28-xanh-d-m-1-1174882643.jpg?v=1750786688&width=1946",
            "//yame.vn/cdn/shop/files/qu-n-jean-the-original-28-xanh-d-m-1-1174882645.jpg?v=1750786693&width=1946",
            "//yame.vn/cdn/shop/files/qu-n-jean-the-original-28-xanh-d-m-1-1174882644.jpg?v=1750786691&width=1946",
            "//yame.vn/cdn/shop/files/qu-n-jean-the-original-28-xanh-d-m-1-1174882646.jpg?v=1750786697&width=1946"
        ],
        "Giá": "261.600",
        "Thuộc tính": {
            "CHẤT JEAN BỀN BỈ CO GIÃN": "Khả năng chịu bền tốt. Sợi Spandex giúp sản phẩm có độ co giãn nhẹ tạo sự thoải mái",
            "GIỮ FORM DÁNG TỐT": "Không bị nhão hay biến dạng sau nhiều lần giặt và luôn giữ được form dáng như mới",
            "ĐA DẠNG MÀU SẮC": "Dễ phối đồ và lựa chọn phù hợp với nhiều phong cách và sở thích khác nhau",
            "LƯU Ý KHI GIẶT": "Nên lộn trái sản phẩm khi giặt để bảo vệ màu sắc và chất liệu của quần jean"
        }
    },
    {
        "Tên sản phẩm": "Quần Jeans Slimfit Co Giãn The Original 28 Đen",
        "Màu sắc": "Đen",
        "Ảnh": [
            "//yame.vn/cdn/shop/files/qu-n-jean-the-original-28-den-1174882647.jpg?v=1750786700&width=1946",
            "//yame.vn/cdn/shop/files/qu-n-jean-the-original-28-den-1174882648.jpg?v=1750854736&width=1946",
            "//yame.vn/cdn/shop/files/qu-n-jean-the-original-28-den-1174882650.jpg?v=1750854962&width=1946",
            "//yame.vn/cdn/shop/files/qu-n-jean-the-original-28-den-1174882649.jpg?v=1750854739&width=1946",
            "//yame.vn/cdn/shop/files/qu-n-jean-the-original-28-den-1174882651.jpg?v=1750854965&width=1946"
        ],
        "Giá": "261.600",
        "Thuộc tính": {
            "CHẤT JEAN BỀN BỈ CO GIÃN": "Khả năng chịu bền tốt. Sợi Spandex giúp sản phẩm có độ co giãn nhẹ tạo sự thoải mái",
            "GIỮ FORM DÁNG TỐT": "Không bị nhão hay biến dạng sau nhiều lần giặt và luôn giữ được form dáng như mới",
            "ĐA DẠNG MÀU SẮC": "Dễ phối đồ và lựa chọn phù hợp với nhiều phong cách và sở thích khác nhau",
            "LƯU Ý KHI GIẶT": "Nên lộn trái sản phẩm khi giặt để bảo vệ màu sắc và chất liệu của quần jean"
        }
    },
    {
        "Tên sản phẩm": "Quần Jeans Slimfit Co Giãn The Original 28 Xanh Dương",
        "Màu sắc": "Xanh Dương",
        "Ảnh": [
            "//yame.vn/cdn/shop/files/qu-n-jean-the-original-28-xanh-d-ng-1174882630.jpg?v=1750854610&width=1946",
            "//yame.vn/cdn/shop/files/qu-n-jean-the-original-28-xanh-d-ng-1174882631.jpg?v=1750854613&width=1946",
            "//yame.vn/cdn/shop/files/qu-n-jean-the-original-28-xanh-d-ng-1174882633.jpg?v=1750854621&width=1946",
            "//yame.vn/cdn/shop/files/qu-n-jean-the-original-28-xanh-d-ng-1174882632.jpg?v=1750854617&width=1946",
            "//yame.vn/cdn/shop/files/qu-n-jean-the-original-28-xanh-d-ng-1174882634.jpg?v=1750854721&width=1946"
        ],
        "Giá": "261.600",
        "Thuộc tính": {
            "CHẤT JEAN BỀN BỈ CO GIÃN": "Khả năng chịu bền tốt. Sợi Spandex giúp sản phẩm có độ co giãn nhẹ tạo sự thoải mái",
            "GIỮ FORM DÁNG TỐT": "Không bị nhão hay biến dạng sau nhiều lần giặt và luôn giữ được form dáng như mới",
            "ĐA DẠNG MÀU SẮC": "Dễ phối đồ và lựa chọn phù hợp với nhiều phong cách và sở thích khác nhau",
            "LƯU Ý KHI GIẶT": "Nên lộn trái sản phẩm khi giặt để bảo vệ màu sắc và chất liệu của quần jean"
        }
    },
    {
        "Tên sản phẩm": "Quần Jeans Slimfit Rách Gối Co Giãn The Original M052 Xanh Đậm",
        "Màu sắc": "Xanh Đậm",
        "Ảnh": [
            "//yame.vn/cdn/shop/files/qu-n-jean-seventy-seven-51-xanh-d-m-1174882571.jpg?v=1750853885&width=1946",
            "//yame.vn/cdn/shop/files/qu-n-jean-seventy-seven-51-xanh-d-m-1174882572.jpg?v=1750853888&width=1946",
            "//yame.vn/cdn/shop/files/qu-n-jean-seventy-seven-51-xanh-d-m-1174882569.jpg?v=1750853780&width=1946",
            "//yame.vn/cdn/shop/files/qu-n-jean-seventy-seven-51-xanh-d-m-1174882567.jpg?v=1750853775&width=1946",
            "//yame.vn/cdn/shop/files/qu-n-jean-seventy-seven-51-xanh-d-m-1174882573.jpg?v=1750853890&width=1946"
        ],
        "Giá": "457.000",
        "Thuộc tính": {
            "DENIM MỀM MẠI CO GIÃN TỐT": "Chất liệu denim mềm mại co giãn tốt mang lại sự thoải mái tuyệt đối khi mặc",
            "THIẾT KẾ CÁ TÍNH": "Thiết kế rách gối độc đáo và túi đồng hồ tinh xảo giúp bạn thể hiện phong cách riêng",
            "ĐƯỜNG MAY TỈ MỈ": "Mỗi đường may đều được chăm chút tỉ mỉ để đảm bảo độ bền cao và mang lại sự thoải mái",
            "LƯU Ý KHI GIẶT": "Nên lộn trái sản phẩm khi giặt để bảo vệ màu sắc và chi tiết rách gối"
        }
    },
    {
        "Tên sản phẩm": "Quần Jeans Slimfit Co Giãn The Original 28 Xanh Đậm",
        "Màu sắc": "Xanh Đậm",
        "Ảnh": [
            "//yame.vn/cdn/shop/files/qu-n-jean-the-original-28-xanh-d-m-1174882636.jpg?v=1750854724&width=1946",
            "//yame.vn/cdn/shop/files/qu-n-jean-the-original-28-xanh-d-m-1174882637.jpg?v=1750854727&width=1946",
            "//yame.vn/cdn/shop/files/qu-n-jean-the-original-28-xanh-d-m-1174882639.jpg?v=1750854733&width=1946",
            "//yame.vn/cdn/shop/files/qu-n-jean-the-original-28-xanh-d-m-1174882638.jpg?v=1750854731&width=1946",
            "//yame.vn/cdn/shop/files/qu-n-jean-the-original-28-xanh-d-m-1174882640.jpg?v=1750786681&width=1946"
        ],
        "Giá": "261.600",
        "Thuộc tính": {
            "CHẤT JEAN BỀN BỈ CO GIÃN": "Khả năng chịu bền tốt. Sợi Spandex giúp sản phẩm có độ co giãn nhẹ tạo sự thoải mái",
            "GIỮ FORM DÁNG TỐT": "Không bị nhão hay biến dạng sau nhiều lần giặt và luôn giữ được form dáng như mới",
            "ĐA DẠNG MÀU SẮC": "Dễ phối đồ và lựa chọn phù hợp với nhiều phong cách và sở thích khác nhau",
            "LƯU Ý KHI GIẶT": "Nên lộn trái sản phẩm khi giặt để bảo vệ màu sắc và chất liệu của quần jean"
        }
    },
    {
        "Tên sản phẩm": "Quần Jeans Slimfit Co Giãn The Original 28 Xám",
        "Màu sắc": "Xám",
        "Ảnh": [
            "//yame.vn/cdn/shop/files/qu-n-jean-the-original-28-xam-1174882665.jpg?v=1750855084&width=1946",
            "//yame.vn/cdn/shop/files/qu-n-jean-the-original-28-xam-1174882666.jpg?v=1750855087&width=1946",
            "//yame.vn/cdn/shop/files/qu-n-jean-the-original-28-xam-1174882667.jpg?v=1750855090&width=1946",
            "//yame.vn/cdn/shop/files/qu-n-jean-the-original-28-xam-1174882668.jpg?v=1750855095&width=1946",
            "//yame.vn/cdn/shop/files/qu-n-jean-the-original-28-xam-1174882669.jpg?v=1750855097&width=1946"
        ],
        "Giá": "261.600",
        "Thuộc tính": {
            "CHẤT JEAN BỀN BỈ CO GIÃN": "Khả năng chịu bền tốt. Sợi Spandex giúp sản phẩm có độ co giãn nhẹ tạo sự thoải mái",
            "GIỮ FORM DÁNG TỐT": "Không bị nhão hay biến dạng sau nhiều lần giặt và luôn giữ được form dáng như mới",
            "ĐA DẠNG MÀU SẮC": "Dễ phối đồ và lựa chọn phù hợp với nhiều phong cách và sở thích khác nhau",
            "LƯU Ý KHI GIẶT": "Nên lộn trái sản phẩm khi giặt để bảo vệ màu sắc và chất liệu của quần jean"
        }
    },
    {
        "Tên sản phẩm": "Quần Jeans Slim Fit Tek Black Jean 009 Đen",
        "Màu sắc": "Đen",
        "Ảnh": [
            "//yame.vn/cdn/shop/files/qu-n-jeans-slim-fit-the-original-m009-den-1176074117.jpg?v=1751364132&width=1946",
            "//yame.vn/cdn/shop/files/qu-n-jeans-slim-fit-the-original-m009-den-1176074116.jpg?v=1751364128&width=1946",
            "//yame.vn/cdn/shop/files/qu-n-jeans-slim-fit-the-original-m009-den-1176074113.jpg?v=1751364019&width=1946",
            "//yame.vn/cdn/shop/files/qu-n-jeans-slim-fit-the-original-m009-den-1176074112.jpg?v=1751364017&width=1946",
            "//yame.vn/cdn/shop/files/qu-n-jeans-slim-fit-the-original-m009-den-1176074111.jpg?v=1751364016&width=1946"
        ],
        "Giá": "477.000",
        "Thuộc tính": {
            "CÔNG NGHỆ 5 KHÔNG ĐỘC ĐÁO": "Không bạc màu không rách không cũ không dây màu không khô cứng siêu bền bỉ",
            "MỀM MẠI THOÁNG KHÍ": "Nhờ vào sợi Modal vải mang lại cảm giác mềm mại vượt trội và khả năng thấm hút ẩm",
            "CO GIÃN LINH HOẠT": "Vải có khả năng co giãn linh hoạt giúp giữ được phom dáng và giảm thiểu tình trạng giãn"
        }
    },
    {
        "Tên sản phẩm": "Quần Jeans Slimfit Co Giãn The Original 28 Xanh Trắng 1",
        "Màu sắc": "",
        "Ảnh": [
            "//yame.vn/cdn/shop/files/qu-n-jean-the-original-28-xam-1174882623.jpg?v=1750854493&width=1946",
            "//yame.vn/cdn/shop/files/qu-n-jean-the-original-28-xam-1174882624.jpg?v=1750854496&width=1946",
            "//yame.vn/cdn/shop/files/qu-n-jean-the-original-28-xam-1174882626.jpg?v=1750854601&width=1946",
            "//yame.vn/cdn/shop/files/qu-n-jean-the-original-28-xam-1174882625.jpg?v=1750854499&width=1946",
            "//yame.vn/cdn/shop/files/qu-n-jean-the-original-28-xam-1174882627.jpg?v=1750854604&width=1946"
        ],
        "Giá": "261.600",
        "Thuộc tính": {
            "CHẤT JEAN BỀN BỈ CO GIÃN": "Khả năng chịu bền tốt. Sợi Spandex giúp sản phẩm có độ co giãn nhẹ tạo sự thoải mái",
            "GIỮ FORM DÁNG TỐT": "Không bị nhão hay biến dạng sau nhiều lần giặt và luôn giữ được form dáng như mới",
            "ĐA DẠNG MÀU SẮC": "Dễ phối đồ và lựa chọn phù hợp với nhiều phong cách và sở thích khác nhau",
            "LƯU Ý KHI GIẶT": "Nên lộn trái sản phẩm khi giặt để bảo vệ màu sắc và chất liệu của quần jean"
        }
    },
    {
        "Tên sản phẩm": "Quần Jeans Slimfit Rách Gối Co Giãn The Original M052 Xanh Trắng",
        "Màu sắc": "Xanh Trắng",
        "Ảnh": [
            "//yame.vn/cdn/shop/files/qu-n-jean-seventy-seven-51-xanh-tr-ng-1174882555.jpg?v=1750853523&width=1946",
            "//yame.vn/cdn/shop/files/qu-n-jean-seventy-seven-51-xanh-tr-ng-1174882556.jpg?v=1750853526&width=1946",
            "//yame.vn/cdn/shop/files/qu-n-jean-seventy-seven-51-xanh-tr-ng-1174882561.jpg?v=1750853540&width=1946",
            "//yame.vn/cdn/shop/files/qu-n-jean-seventy-seven-51-xanh-tr-ng-1174882559.jpg?v=1750853534&width=1946",
            "//yame.vn/cdn/shop/files/qu-n-jean-seventy-seven-51-xanh-tr-ng-1174882558.jpg?v=1750853531&width=1946"
        ],
        "Giá": "457.000",
        "Thuộc tính": {
            "DENIM MỀM MẠI CO GIÃN TỐT": "Chất liệu denim mềm mại co giãn tốt mang lại sự thoải mái tuyệt đối khi mặc",
            "THIẾT KẾ CÁ TÍNH": "Thiết kế rách gối độc đáo và túi đồng hồ tinh xảo giúp bạn thể hiện phong cách riêng",
            "ĐƯỜNG MAY TỈ MỈ": "Mỗi đường may đều được chăm chút tỉ mỉ để đảm bảo độ bền cao và mang lại sự thoải mái",
            "LƯU Ý KHI GIẶT": "Nên lộn trái sản phẩm khi giặt để bảo vệ màu sắc và chi tiết rách gối"
        }
    },
    {
        "Tên sản phẩm": "Quần Jeans Slim Fit Mềm Mịn Mát The Original 02 Xanh Đen",
        "Màu sắc": "Xanh Đen",
        "Ảnh": [
            "//yame.vn/cdn/shop/files/qu-n-jean-the-original-02-xanh-den-1174882618.jpg?v=1750786816&width=1946",
            "//yame.vn/cdn/shop/files/qu-n-jean-the-original-02-xanh-den-1174882619.jpg?v=1750786820&width=1946",
            "//yame.vn/cdn/shop/files/qu-n-jean-the-original-02-xanh-den-1174882620.jpg?v=1750854487&width=1946",
            "//yame.vn/cdn/shop/files/qu-n-jean-the-original-02-xanh-den-1174882617.jpg?v=1750786814&width=1946",
            "//yame.vn/cdn/shop/files/qu-n-jean-the-original-02-xanh-den-1174882614.jpg?v=1750854485&width=1946"
        ],
        "Giá": "457.000",
        "Thuộc tính": {
            "MỀM - MỊN - MÁT": "Chất liệu Jean Cotton Spandex mềm mại mịn màng và mát mẻ mặc cực kỳ dễ chịu",
            "ĐA DẠNG MÀU SẮC": "Sản phẩm có 4 màu phục vụ nhiều sở thích về màu sắc dễ dàng lựa chọn và phối đồ",
            "CO GIÃN ĐA CHIỀU": "Tạo sự thoải mái khi vận động không gây cảm giác gò bó khó chịu khi mặc",
            "LƯU Ý KHI GIẶT": "Nên lộn trái sản phẩm khi giặt để bảo vệ màu sắc và chất liệu của quần jean"
        }
    },
    {
        "Tên sản phẩm": "Quần Jeans Slimfit Co Giãn The Original 28 Xanh Trắng",
        "Màu sắc": "Xanh Trắng",
        "Ảnh": [
            "//yame.vn/cdn/shop/files/qu-n-jean-the-original-28-xanh-tr-ng-1174882653.jpg?v=1750854968&width=1946",
            "//yame.vn/cdn/shop/files/qu-n-jean-the-original-28-xanh-tr-ng-1174882654.jpg?v=1750854972&width=1946",
            "//yame.vn/cdn/shop/files/qu-n-jean-the-original-28-xanh-tr-ng-1174882655.jpg?v=1750854975&width=1946",
            "//yame.vn/cdn/shop/files/qu-n-jean-the-original-28-xanh-tr-ng-1174882657.jpg?v=1750854980&width=1946",
            "//yame.vn/cdn/shop/files/qu-n-jean-the-original-28-xanh-tr-ng-1174882656.jpg?v=1750854978&width=1946"
        ],
        "Giá": "261.600",
        "Thuộc tính": {
            "CHẤT JEAN BỀN BỈ CO GIÃN": "Khả năng chịu bền tốt. Sợi Spandex giúp sản phẩm có độ co giãn nhẹ tạo sự thoải mái",
            "GIỮ FORM DÁNG TỐT": "Không bị nhão hay biến dạng sau nhiều lần giặt và luôn giữ được form dáng như mới",
            "ĐA DẠNG MÀU SẮC": "Dễ phối đồ và lựa chọn phù hợp với nhiều phong cách và sở thích khác nhau",
            "LƯU Ý KHI GIẶT": "Nên lộn trái sản phẩm khi giặt để bảo vệ màu sắc và chất liệu của quần jean"
        }
    },
    {
        "Tên sản phẩm": "Quần Jeans Slimfit Co Giãn The Original M100 Xanh Đậm",
        "Màu sắc": "Xanh Đậm",
        "Ảnh": [
            "//yame.vn/cdn/shop/files/qu-n-jean-no-style-m100-xanh-d-m-1174882677.jpg?v=1750786577&width=1946",
            "//yame.vn/cdn/shop/files/qu-n-jean-no-style-m100-xanh-d-m-1174882678.jpg?v=1750786579&width=1946",
            "//yame.vn/cdn/shop/files/qu-n-jean-no-style-m100-xanh-d-m-1174882679.jpg?v=1750855099&width=1946",
            "//yame.vn/cdn/shop/files/qu-n-jean-no-style-m100-xanh-d-m-1174882680.jpg?v=1750855321&width=1946",
            "//yame.vn/cdn/shop/files/0023537.jpg?v=1758104789&width=1946"
        ],
        "Giá": "357.000",
        "Thuộc tính": {
            "VẢI JEAN BỀN CO GIÃN NHẸ": "Chất liệu vải Jean cao cấp giúp quần có độ bền vượt trội co giãn nhẹ thoải mái",
            "ĐỨNG FORM LỊCH LÃM": "Thiết kế ống đứng và chất liệu vải dày giúp quần giữ form dáng chuẩn gọn gàng",
            "WASH NHẸ TINH TẾ": "Quần được wash nhẹ mang lại vẻ ngoài đơn giản nhưng tinh tế và không kém phần thời trang",
            "LƯU Ý KHI GIẶT": "Nên lộn trái sản phẩm khi giặt để bảo vệ màu sắc và chất liệu của quần jean"
        }
    },
    {
        "Tên sản phẩm": "Quần Jeans Slimfit Rách Gối Co Giãn The Original M052 Xanh Dương",
        "Màu sắc": "Xanh Dương",
        "Ảnh": [
            "//yame.vn/cdn/shop/files/qu-n-jean-seventy-seven-51-xanh-d-ng-1174882579.jpg?v=1750854125&width=1946",
            "//yame.vn/cdn/shop/files/qu-n-jean-seventy-seven-51-xanh-d-ng-1174882580.jpg?v=1750786921&width=1946",
            "//yame.vn/cdn/shop/files/qu-n-jean-seventy-seven-51-xanh-d-ng-1174882578.jpg?v=1750854122&width=1946",
            "//yame.vn/cdn/shop/files/qu-n-jean-seventy-seven-51-xanh-d-ng-1174882581.jpg?v=1750786924&width=1946",
            "//yame.vn/cdn/shop/files/qu-n-jean-seventy-seven-51-xanh-d-ng-1174882575.jpg?v=1750853893&width=1946"
        ],
        "Giá": "457.000",
        "Thuộc tính": {
            "DENIM MỀM MẠI CO GIÃN TỐT": "Chất liệu denim mềm mại co giãn tốt mang lại sự thoải mái tuyệt đối khi mặc",
            "THIẾT KẾ CÁ TÍNH": "Thiết kế rách gối độc đáo và túi đồng hồ tinh xảo giúp bạn thể hiện phong cách riêng",
            "ĐƯỜNG MAY TỈ MỈ": "Mỗi đường may đều được chăm chút tỉ mỉ để đảm bảo độ bền cao và mang lại sự thoải mái",
            "LƯU Ý KHI GIẶT": "Nên lộn trái sản phẩm khi giặt để bảo vệ màu sắc và chi tiết rách gối"
        }
    },
    {
        "Tên sản phẩm": "Quần Jeans Slim Fit Mềm Mịn Mát The Original 02 Đen",
        "Màu sắc": "Đen",
        "Ảnh": [
            "//yame.vn/cdn/shop/files/qu-n-jean-the-original-02-den-1174882607.jpg?v=1750854373&width=1946",
            "//yame.vn/cdn/shop/files/qu-n-jean-the-original-02-den-1174882608.jpg?v=1750854376&width=1946",
            "//yame.vn/cdn/shop/files/qu-n-jean-the-original-02-den-1174882610.jpg?v=1750854481&width=1946",
            "//yame.vn/cdn/shop/files/qu-n-jean-the-original-02-den-1174882609.jpg?v=1750854379&width=1946",
            "//yame.vn/cdn/shop/files/qu-n-jean-the-original-02-den-1174882606.jpg?v=1750854370&width=1946"
        ],
        "Giá": "457.000",
        "Thuộc tính": {
            "MỀM - MỊN - MÁT": "Chất liệu Jean Cotton Spandex mềm mại mịn màng và mát mẻ mặc cực kỳ dễ chịu",
            "ĐA DẠNG MÀU SẮC": "Sản phẩm có 4 màu phục vụ nhiều sở thích về màu sắc dễ dàng lựa chọn và phối đồ",
            "CO GIÃN ĐA CHIỀU": "Tạo sự thoải mái khi vận động không gây cảm giác gò bó khó chịu khi mặc",
            "LƯU Ý KHI GIẶT": "Nên lộn trái sản phẩm khi giặt để bảo vệ màu sắc và chất liệu của quần jean"
        }
    },
    {
        "Tên sản phẩm": "Quần Jeans Slimfit S.Café® Co Giãn Khử Mùi The Original M040 Xanh Nhạt",
        "Màu sắc": "Xanh Nhạt",
        "Ảnh": [
            "//yame.vn/cdn/shop/files/0024730_Thumb_1.jpg?v=1758007490&width=1946",
            "//yame.vn/cdn/shop/files/0024730_Thumb_2.jpg?v=1758007490&width=1946",
            "//yame.vn/cdn/shop/files/0024730_Thumb_6.jpg?v=1758007490&width=1946",
            "//yame.vn/cdn/shop/files/0024730_Thumb_3.jpg?v=1758007490&width=1946",
            "//yame.vn/cdn/shop/files/0024730_Thumb_4.jpg?v=1758007490&width=1946"
        ],
        "Giá": "497.000",
        "Thuộc tính": {
            "BÍ MẬT TỪ SỢI CAFE": "Công nghệ S.Café® vừa khử mùi hiệu quả vừa giúp chống tia UV tự nhiên và bảo vệ bạn toàn diện",
            "BỀN VỮNG VÌ MÔI TRƯỜNG": "Hành trình từ phế phẩm trở thành thời trang giảm thiểu khí CO₂ và chất thải ra môi trường",
            "LƯU Ý KHI GIẶT": "Do đặc tính tự nhiên của sợi nên hiệu năng khử mùi chống UV sẽ tối ưu nhất trong 40 lần giặt đầu"
        }
    },
    {
        "Tên sản phẩm": "Quần Jeans Slimfit Co Giãn The Original M100 Xanh Nhạt",
        "Màu sắc": "Xanh Nhạt",
        "Ảnh": [
            "//yame.vn/cdn/shop/files/qu-n-jean-no-style-m100-xanh-nh-t-1174882671.jpg?v=1750786562&width=1946",
            "//yame.vn/cdn/shop/files/qu-n-jean-no-style-m100-xanh-nh-t-1174882672.jpg?v=1750786564&width=1946",
            "//yame.vn/cdn/shop/files/qu-n-jean-no-style-m100-xanh-nh-t-1174882673.jpg?v=1750786568&width=1946",
            "//yame.vn/cdn/shop/files/qu-n-jean-no-style-m100-xanh-nh-t-1174882674.jpg?v=1750786571&width=1946",
            "//yame.vn/cdn/shop/files/0023538.jpg?v=1758104835&width=1946"
        ],
        "Giá": "357.000",
        "Thuộc tính": {
            "VẢI JEAN BỀN CO GIÃN NHẸ": "Chất liệu vải Jean cao cấp giúp quần có độ bền vượt trội co giãn nhẹ thoải mái",
            "ĐỨNG FORM LỊCH LÃM": "Thiết kế ống đứng và chất liệu vải dày giúp quần giữ form dáng chuẩn gọn gàng",
            "WASH NHẸ TINH TẾ": "Quần được wash nhẹ mang lại vẻ ngoài đơn giản nhưng tinh tế và không kém phần thời trang",
            "LƯU Ý KHI GIẶT": "Nên lộn trái sản phẩm khi giặt để bảo vệ màu sắc và chất liệu của quần jean"
        }
    },
    {
        "Tên sản phẩm": "Quần Jeans Slimfit Coolmax® Thoáng Mát The Original 007 Xanh Nhạt",
        "Màu sắc": "Xanh Nhạt",
        "Ảnh": [
            "//yame.vn/cdn/shop/files/qu-n-jeans-the-original-m003-xanh-nh-t-1176074109.jpg?v=1751364009&width=1946",
            "//yame.vn/cdn/shop/files/qu-n-jeans-the-original-m003-xanh-nh-t-1176074108.jpg?v=1751364006&width=1946",
            "//yame.vn/cdn/shop/files/qu-n-jeans-the-original-m003-xanh-nh-t-1176074105.jpg?v=1751363899&width=1946",
            "//yame.vn/cdn/shop/files/qu-n-jeans-the-original-m003-xanh-nh-t-1176074104.jpg?v=1751363896&width=1946",
            "//yame.vn/cdn/shop/files/qu-n-jeans-the-original-m003-xanh-nh-t-1176074101.jpg?v=1751363887&width=1946"
        ],
        "Giá": "557.000",
        "Thuộc tính": {
            "Công Nghệ Coolmax® EcoMade": "Thoáng Mát Tối Đa - Khô Thoáng Tức Thì",
            "CHỈ 2% TẠO NÊN SỰ KHÁC BIỆT": "Sợi Lycra cao cấp ôm vừa vặn thoải mái vận động giữ phom dáng chuẩn sau nhiều lần giặt",
            "MỀM MỊN - CHẠM LÀ MÊ": "Chất Cotton và Rayon siêu mềm mại nuông chiều làn da mặc là ghiền ngay"
        }
    },
    {
        "Tên sản phẩm": "Quần Jeans Slimfit S.Café® Co Giãn Khử Mùi The Original M040 Xanh Dương",
        "Màu sắc": "Xanh Dương",
        "Ảnh": [
            "//yame.vn/cdn/shop/files/0024729_Thumb_1.jpg?v=1758007315&width=1946",
            "//yame.vn/cdn/shop/files/0024729_Thumb_2.jpg?v=1758007315&width=1946",
            "//yame.vn/cdn/shop/files/0024729_Thumb_3.jpg?v=1758007315&width=1946",
            "//yame.vn/cdn/shop/files/0024729_Thumb_4.jpg?v=1758007315&width=1946",
            "//yame.vn/cdn/shop/files/0024729_Thumb_5.jpg?v=1758007315&width=1946"
        ],
        "Giá": "497.000",
        "Thuộc tính": {
            "BÍ MẬT TỪ SỢI CAFE": "Công nghệ S.Café® vừa khử mùi hiệu quả vừa giúp chống tia UV tự nhiên và bảo vệ bạn toàn diện",
            "BỀN VỮNG VÌ MÔI TRƯỜNG": "Hành trình từ phế phẩm trở thành thời trang giảm thiểu khí CO₂ và chất thải ra môi trường",
            "LƯU Ý KHI GIẶT": "Do đặc tính tự nhiên của sợi nên hiệu năng khử mùi chống UV sẽ tối ưu nhất trong 40 lần giặt đầu"
        }
    },
    {
        "Tên sản phẩm": "Quần Jeans Slimfit S.Café® Co Giãn Khử Mùi The Original M040 Xanh Đậm",
        "Màu sắc": "Xanh Đậm",
        "Ảnh": [
            "//yame.vn/cdn/shop/files/0024728Thumb1.jpg?v=1758006428&width=1946",
            "//yame.vn/cdn/shop/files/0024728Thumb2_2.jpg?v=1758006427&width=1946",
            "//yame.vn/cdn/shop/files/0024728Thumb3_2.jpg?v=1758006427&width=1946",
            "//yame.vn/cdn/shop/files/0024728Thumb4_2.jpg?v=1758006427&width=1946",
            "//yame.vn/cdn/shop/files/0024728Thumb5_2.jpg?v=1758006427&width=1946"
        ],
        "Giá": "497.000",
        "Thuộc tính": {
            "BÍ MẬT TỪ SỢI CAFE": "Công nghệ S.Café® vừa khử mùi hiệu quả vừa giúp chống tia UV tự nhiên và bảo vệ bạn toàn diện",
            "BỀN VỮNG VÌ MÔI TRƯỜNG": "Hành trình từ phế phẩm trở thành thời trang giảm thiểu khí CO₂ và chất thải ra môi trường",
            "LƯU Ý KHI GIẶT": "Do đặc tính tự nhiên của sợi nên hiệu năng khử mùi chống UV sẽ tối ưu nhất trong 40 lần giặt đầu"
        }
    },
    {
        "Tên sản phẩm": "Quần Jeans Slimfit Coolmax® Thoáng Mát The Original 007 Xanh Dương",
        "Màu sắc": "Xanh Dương",
        "Ảnh": [
            "//yame.vn/cdn/shop/files/qu-n-jeans-the-original-m003-xanh-d-ng-1176074086.jpg?v=1751363647&width=1946",
            "//yame.vn/cdn/shop/files/qu-n-jeans-the-original-m003-xanh-d-ng-1176074085.jpg?v=1751363644&width=1946",
            "//yame.vn/cdn/shop/files/qu-n-jeans-the-original-m003-xanh-d-ng-1176074087.jpg?v=1751363652&width=1946",
            "//yame.vn/cdn/shop/files/qu-n-jeans-the-original-m003-xanh-d-ng-1176074088.jpg?v=1751363653&width=1946",
            "//yame.vn/cdn/shop/files/qu-n-jeans-the-original-m003-xanh-d-ng-1176074089.jpg?v=1751363656&width=1946"
        ],
        "Giá": "557.000",
        "Thuộc tính": {
            "Công Nghệ Coolmax® EcoMade": "Thoáng Mát Tối Đa - Khô Thoáng Tức Thì",
            "CHỈ 2% TẠO NÊN SỰ KHÁC BIỆT": "Sợi Lycra cao cấp ôm vừa vặn thoải mái vận động giữ phom dáng chuẩn sau nhiều lần giặt",
            "MỀM MỊN - CHẠM LÀ MÊ": "Chất Cotton và Rayon siêu mềm mại nuông chiều làn da mặc là ghiền ngay"
        }
    },
    {
        "Tên sản phẩm": "Quần Jeans Slimfit Coolmax® Thoáng Mát The Original 007 Xanh Đậm",
        "Màu sắc": "Xanh Đậm",
        "Ảnh": [
            "//yame.vn/cdn/shop/files/qu-n-jeans-the-original-m003-xanh-d-m-1176074099.jpg?v=1751363884&width=1946",
            "//yame.vn/cdn/shop/files/qu-n-jeans-the-original-m003-xanh-d-m-1176074098.jpg?v=1751363881&width=1946",
            "//yame.vn/cdn/shop/files/qu-n-jeans-the-original-m003-xanh-d-m-1176074095.jpg?v=1751363773&width=1946",
            "//yame.vn/cdn/shop/files/qu-n-jeans-the-original-m003-xanh-d-m-1176074094.jpg?v=1751363770&width=1946",
            "//yame.vn/cdn/shop/files/qu-n-jeans-the-original-m003-xanh-d-m-1176074092.jpg?v=1751363764&width=1946"
        ],
        "Giá": "557.000",
        "Thuộc tính": {
            "Công Nghệ Coolmax® EcoMade": "Thoáng Mát Tối Đa - Khô Thoáng Tức Thì",
            "CHỈ 2% TẠO NÊN SỰ KHÁC BIỆT": "Sợi Lycra cao cấp ôm vừa vặn thoải mái vận động giữ phom dáng chuẩn sau nhiều lần giặt",
            "MỀM MỊN - CHẠM LÀ MÊ": "Chất Cotton và Rayon siêu mềm mại nuông chiều làn da mặc là ghiền ngay"
        }
    },
    {
        "Tên sản phẩm": "Quần Jeans Slim Fit Mềm Mịn Mát The Original 02 Xanh Đậm",
        "Màu sắc": "Xanh Đậm",
        "Ảnh": [
            "//yame.vn/cdn/shop/files/qu-n-jean-the-original-02-xanh-d-m-1174882592.jpg?v=1750854137&width=1946",
            "//yame.vn/cdn/shop/files/qu-n-jean-the-original-02-xanh-d-m-1174882593.jpg?v=1750854141&width=1946",
            "//yame.vn/cdn/shop/files/qu-n-jean-the-original-02-xanh-d-m-1174882591.jpg?v=1750854135&width=1946",
            "//yame.vn/cdn/shop/files/qu-n-jean-the-original-02-xanh-d-m-1174882587.jpg?v=1750786939&width=1946",
            "//yame.vn/cdn/shop/files/qu-n-jean-the-original-02-xanh-d-m-1174882590.jpg?v=1750854132&width=1946"
        ],
        "Giá": "457.000",
        "Thuộc tính": {
            "MỀM - MỊN - MÁT": "Chất liệu Jean Cotton Spandex mềm mại mịn màng và mát mẻ mặc cực kỳ dễ chịu",
            "CO GIÃN ĐA CHIỀU": "Tạo sự thoải mái khi vận động không gây cảm giác gò bó khó chịu khi mặc",
            "ĐA DẠNG MÀU SẮC": "Sản phẩm có 4 màu phục vụ nhiều sở thích về màu sắc dễ dàng lựa chọn và phối đồ",
            "LƯU Ý KHI GIẶT": "Nên lộn trái sản phẩm khi giặt để bảo vệ màu sắc và chất liệu của quần jean"
        }
    },
    {
        "Tên sản phẩm": "Quần Jeans Slim Fit Mềm Mịn Mát The Original 02 Xanh Nhạt",
        "Màu sắc": "Xanh Nhạt",
        "Ảnh": [
            "//yame.vn/cdn/shop/files/qu-n-jean-the-original-02-xanh-nh-t-1174882602.jpg?v=1750854361&width=1946",
            "//yame.vn/cdn/shop/files/qu-n-jean-the-original-02-xanh-nh-t-1174882595.jpg?v=1750854242&width=1946",
            "//yame.vn/cdn/shop/files/qu-n-jean-the-original-02-xanh-nh-t-1174882598.jpg?v=1750854252&width=1946",
            "//yame.vn/cdn/shop/files/qu-n-jean-the-original-02-xanh-nh-t-1174882597.jpg?v=1750854249&width=1946",
            "//yame.vn/cdn/shop/files/qu-n-jean-the-original-02-xanh-nh-t-1174882601.jpg?v=1750854261&width=1946"
        ],
        "Giá": "457.000",
        "Thuộc tính": {
            "MỀM - MỊN - MÁT": "Chất liệu Jean Cotton Spandex mềm mại mịn màng và mát mẻ mặc cực kỳ dễ chịu",
            "CO GIÃN ĐA CHIỀU": "Tạo sự thoải mái khi vận động không gây cảm giác gò bó khó chịu khi mặc",
            "ĐA DẠNG MÀU SẮC": "Sản phẩm có 4 màu phục vụ nhiều sở thích về màu sắc dễ dàng lựa chọn và phối đồ",
            "LƯU Ý KHI GIẶT": "Nên lộn trái sản phẩm khi giặt để bảo vệ màu sắc và chất liệu của quần jean"
        }
    }
]